Metadata-Version: 2.1
Name: mathinput
Version: 0.0.1
Summary: Project Description
Author: Mads Kristensen <mads@smart-sync.com>
License: MIT
Classifier: Framework :: Dash
License-File: LICENSE
